MANIFEST.in
README.md
requirements.txt
setup.cfg
setup.py
chromedriver_install/__init__.py
chromedriver_install/main.py
chromedriver_install.egg-info/PKG-INFO
chromedriver_install.egg-info/SOURCES.txt
chromedriver_install.egg-info/dependency_links.txt
chromedriver_install.egg-info/entry_points.txt
chromedriver_install.egg-info/not-zip-safe
chromedriver_install.egg-info/requires.txt
chromedriver_install.egg-info/top_level.txt