Metadata-Version: 2.1
Name: chromedriver-install
Version: 0.3
Summary: Package for installing the latest chromedriver automatically.
Home-page: http://github.com/shadowmoose/chrome_driver
Author: ShadowMoose
Author-email: shadowmoose@github.com
License: MIT
Platform: UNKNOWN
